odoo/addons/base_rest_auth_user_service/README.rst
odoo/addons/base_rest_auth_user_service/__init__.py
odoo/addons/base_rest_auth_user_service/__manifest__.py
odoo/addons/base_rest_auth_user_service/controllers/__init__.py
odoo/addons/base_rest_auth_user_service/controllers/main.py
odoo/addons/base_rest_auth_user_service/i18n/base_rest_auth_user_service.pot
odoo/addons/base_rest_auth_user_service/readme/CONTRIBUTORS.rst
odoo/addons/base_rest_auth_user_service/readme/DESCRIPTION.rst
odoo/addons/base_rest_auth_user_service/readme/HISTORY.rst
odoo/addons/base_rest_auth_user_service/readme/USAGE.rst
odoo/addons/base_rest_auth_user_service/services/__init__.py
odoo/addons/base_rest_auth_user_service/services/session.py
odoo/addons/base_rest_auth_user_service/static/description/icon.png
odoo/addons/base_rest_auth_user_service/static/description/index.html
odoo/addons/base_rest_auth_user_service/tests/__init__.py
odoo/addons/base_rest_auth_user_service/tests/test_rest_session.py
odoo13_addon_base_rest_auth_user_service-13.0.1.0.1.dist-info/METADATA
odoo13_addon_base_rest_auth_user_service-13.0.1.0.1.dist-info/WHEEL
odoo13_addon_base_rest_auth_user_service-13.0.1.0.1.dist-info/top_level.txt
odoo13_addon_base_rest_auth_user_service-13.0.1.0.1.dist-info/RECORD
